[
  {
    "id": "550e8400-e29b-41d4-a716-446655440001",
    "username": "emma_johnson",
    "display_name": "Emma Johnson",
    "email": "emma.johnson@example.com",
    "country": "United States",
    "state": "California",
    "avatar_url": "https://cdn.example.com/avatars/emma_johnson.jpg",
    "lang_tag": "en-US",
    "timezone": "America/Los_Angeles",
    "created_at": "2025-01-01T08:15:00Z",
    "updated_at": "2025-02-10T09:30:00Z",
    "verified_at": "2025-01-02T10:00:00Z"
  },
  {
    "id": "550e8400-e29b-41d4-a716-446655440002",
    "username": "liam_smith",
    "display_name": "Liam Smith",
    "email": "liam.smith@example.com",
    "country": "Canada",
    "state": "Ontario",
    "avatar_url": "https://cdn.example.com/avatars/liam_smith.jpg",
    "lang_tag": "en-CA",
    "timezone": "America/Toronto",
    "created_at": "2025-01-03T11:20:00Z",
    "updated_at": "2025-02-11T08:40:00Z",
    "verified_at": "2025-01-04T07:15:00Z"
  },
  {
    "id": "550e8400-e29b-41d4-a716-446655440003",
    "username": "sofia_garcia",
    "display_name": "Sofia Garcia",
    "email": "sofia.garcia@example.com",
    "country": "Spain",
    "state": "Madrid",
    "avatar_url": "https://cdn.example.com/avatars/sofia_garcia.jpg",
    "lang_tag": "es-ES",
    "timezone": "Europe/Madrid",
    "created_at": "2025-01-05T09:45:00Z",
    "updated_at": "2025-02-12T12:10:00Z",
    "verified_at": "2025-01-06T08:00:00Z"
  },
  {
    "id": "550e8400-e29b-41d4-a716-446655440004",
    "username": "arjun_patel",
    "display_name": "Arjun Patel",
    "email": "arjun.patel@example.com",
    "country": "India",
    "state": "Gujarat",
    "avatar_url": "https://cdn.example.com/avatars/arjun_patel.jpg",
    "lang_tag": "en-IN",
    "timezone": "Asia/Kolkata",
    "created_at": "2025-01-07T05:30:00Z",
    "updated_at": "2025-02-13T14:20:00Z",
    "verified_at": "2025-01-08T06:45:00Z"
  },
  {
    "id": "550e8400-e29b-41d4-a716-446655440005",
    "username": "wei_chen",
    "display_name": "Wei Chen",
    "email": "wei.chen@example.com",
    "country": "China",
    "state": "Guangdong",
    "avatar_url": "https://cdn.example.com/avatars/wei_chen.jpg",
    "lang_tag": "zh-CN",
    "timezone": "Asia/Shanghai",
    "created_at": "2025-01-09T02:10:00Z",
    "updated_at": "2025-02-14T09:55:00Z",
    "verified_at": "2025-01-10T08:30:00Z"
  },
  {
    "id": "550e8400-e29b-41d4-a716-446655440006",
    "username": "yuki_tanaka",
    "display_name": "Yuki Tanaka",
    "email": "yuki.tanaka@example.com",
    "country": "Japan",
    "state": "Tokyo",
    "avatar_url": "https://cdn.example.com/avatars/yuki_tanaka.jpg",
    "lang_tag": "ja-JP",
    "timezone": "Asia/Tokyo",
    "created_at": "2025-01-11T01:20:00Z",
    "updated_at": "2025-02-15T11:00:00Z",
    "verified_at": "2025-01-12T07:40:00Z"
  },
  {
    "id": "550e8400-e29b-41d4-a716-446655440007",
    "username": "oliver_wilson",
    "display_name": "Oliver Wilson",
    "email": "oliver.wilson@example.com",
    "country": "Australia",
    "state": "New South Wales",
    "avatar_url": "https://cdn.example.com/avatars/oliver_wilson.jpg",
    "lang_tag": "en-AU",
    "timezone": "Australia/Sydney",
    "created_at": "2025-01-13T04:10:00Z",
    "updated_at": "2025-02-16T06:30:00Z",
    "verified_at": "2025-01-14T09:20:00Z"
  },
  {
    "id": "550e8400-e29b-41d4-a716-446655440008",
    "username": "hans_mueller",
    "display_name": "Hans Mueller",
    "email": "hans.mueller@example.com",
    "country": "Germany",
    "state": "Bavaria",
    "avatar_url": "https://cdn.example.com/avatars/hans_mueller.jpg",
    "lang_tag": "de-DE",
    "timezone": "Europe/Berlin",
    "created_at": "2025-01-15T07:50:00Z",
    "updated_at": "2025-02-17T10:25:00Z",
    "verified_at": "2025-01-16T08:35:00Z"
  },
  {
    "id": "550e8400-e29b-41d4-a716-446655440009",
    "username": "lucas_dupont",
    "display_name": "Lucas Dupont",
    "email": "lucas.dupont@example.com",
    "country": "France",
    "state": "Ile-de-France",
    "avatar_url": "https://cdn.example.com/avatars/lucas_dupont.jpg",
    "lang_tag": "fr-FR",
    "timezone": "Europe/Paris",
    "created_at": "2025-01-17T09:00:00Z",
    "updated_at": "2025-02-18T11:40:00Z",
    "verified_at": "2025-01-18T07:10:00Z"
  },
  {
    "id": "550e8400-e29b-41d4-a716-446655440010",
    "username": "isabella_silva",
    "display_name": "Isabella Silva",
    "email": "isabella.silva@example.com",
    "country": "Brazil",
    "state": "Sao Paulo",
    "avatar_url": "https://cdn.example.com/avatars/isabella_silva.jpg",
    "lang_tag": "pt-BR",
    "timezone": "America/Sao_Paulo",
    "created_at": "2025-01-19T10:30:00Z",
    "updated_at": "2025-02-19T13:15:00Z",
    "verified_at": "2025-01-20T09:00:00Z"
  },
  {
    "id": "550e8400-e29b-41d4-a716-446655440011",
    "username": "noah_brown",
    "display_name": "Noah Brown",
    "email": "noah.brown@example.com",
    "country": "United Kingdom",
    "state": "England",
    "avatar_url": "https://cdn.example.com/avatars/noah_brown.jpg",
    "lang_tag": "en-GB",
    "timezone": "Europe/London",
    "created_at": "2025-01-21T08:00:00Z",
    "updated_at": "2025-02-20T10:00:00Z",
    "verified_at": "2025-01-22T09:00:00Z"
  },
  {
    "id": "550e8400-e29b-41d4-a716-446655440012",
    "username": "mia_taylor",
    "display_name": "Mia Taylor",
    "email": "mia.taylor@example.com",
    "country": "New Zealand",
    "state": "Auckland",
    "avatar_url": "https://cdn.example.com/avatars/mia_taylor.jpg",
    "lang_tag": "en-NZ",
    "timezone": "Pacific/Auckland",
    "created_at": "2025-01-22T11:15:00Z",
    "updated_at": "2025-02-21T08:10:00Z",
    "verified_at": "2025-01-23T07:45:00Z"
  },
  {
    "id": "550e8400-e29b-41d4-a716-446655440013",
    "username": "ethan_rossi",
    "display_name": "Ethan Rossi",
    "email": "ethan.rossi@example.com",
    "country": "Italy",
    "state": "Lombardy",
    "avatar_url": "https://cdn.example.com/avatars/ethan_rossi.jpg",
    "lang_tag": "it-IT",
    "timezone": "Europe/Rome",
    "created_at": "2025-01-24T06:30:00Z",
    "updated_at": "2025-02-22T14:00:00Z",
    "verified_at": "2025-01-25T08:20:00Z"
  },
  {
    "id": "550e8400-e29b-41d4-a716-446655440014",
    "username": "ava_andersson",
    "display_name": "Ava Andersson",
    "email": "ava.andersson@example.com",
    "country": "Sweden",
    "state": "Stockholm",
    "avatar_url": "https://cdn.example.com/avatars/ava_andersson.jpg",
    "lang_tag": "sv-SE",
    "timezone": "Europe/Stockholm",
    "created_at": "2025-01-25T09:40:00Z",
    "updated_at": "2025-02-23T12:50:00Z",
    "verified_at": "2025-01-26T07:30:00Z"
  },
  {
    "id": "550e8400-e29b-41d4-a716-446655440015",
    "username": "mateo_gonzalez",
    "display_name": "Mateo Gonzalez",
    "email": "mateo.gonzalez@example.com",
    "country": "Mexico",
    "state": "Jalisco",
    "avatar_url": "https://cdn.example.com/avatars/mateo_gonzalez.jpg",
    "lang_tag": "es-MX",
    "timezone": "America/Mexico_City",
    "created_at": "2025-01-27T05:20:00Z",
    "updated_at": "2025-02-24T09:15:00Z",
    "verified_at": "2025-01-28T06:50:00Z"
  },
  {
    "id": "550e8400-e29b-41d4-a716-446655440016",
    "username": "zara_khan",
    "display_name": "Zara Khan",
    "email": "zara.khan@example.com",
    "country": "Pakistan",
    "state": "Punjab",
    "avatar_url": "https://cdn.example.com/avatars/zara_khan.jpg",
    "lang_tag": "en-PK",
    "timezone": "Asia/Karachi",
    "created_at": "2025-01-29T04:10:00Z",
    "updated_at": "2025-02-25T10:20:00Z",
    "verified_at": "2025-01-30T08:40:00Z"
  },
  {
    "id": "550e8400-e29b-41d4-a716-446655440017",
    "username": "omar_hassan",
    "display_name": "Omar Hassan",
    "email": "omar.hassan@example.com",
    "country": "Egypt",
    "state": "Cairo",
    "avatar_url": "https://cdn.example.com/avatars/omar_hassan.jpg",
    "lang_tag": "ar-EG",
    "timezone": "Africa/Cairo",
    "created_at": "2025-01-31T07:00:00Z",
    "updated_at": "2025-02-26T11:00:00Z",
    "verified_at": "2025-02-01T07:30:00Z"
  },
  {
    "id": "550e8400-e29b-41d4-a716-446655440018",
    "username": "nora_larsen",
    "display_name": "Nora Larsen",
    "email": "nora.larsen@example.com",
    "country": "Denmark",
    "state": "Capital Region",
    "avatar_url": "https://cdn.example.com/avatars/nora_larsen.jpg",
    "lang_tag": "da-DK",
    "timezone": "Europe/Copenhagen",
    "created_at": "2025-02-01T08:50:00Z",
    "updated_at": "2025-02-27T12:10:00Z",
    "verified_at": "2025-02-02T09:00:00Z"
  },
  {
    "id": "550e8400-e29b-41d4-a716-446655440019",
    "username": "leo_santos",
    "display_name": "Leo Santos",
    "email": "leo.santos@example.com",
    "country": "Philippines",
    "state": "Metro Manila",
    "avatar_url": "https://cdn.example.com/avatars/leo_santos.jpg",
    "lang_tag": "en-PH",
    "timezone": "Asia/Manila",
    "created_at": "2025-02-03T06:45:00Z",
    "updated_at": "2025-02-28T13:25:00Z",
    "verified_at": "2025-02-04T08:15:00Z"
  },
  {
    "id": "550e8400-e29b-41d4-a716-446655440020",
    "username": "hana_kim",
    "display_name": "Hana Kim",
    "email": "hana.kim@example.com",
    "country": "South Korea",
    "state": "Seoul",
    "avatar_url": "https://cdn.example.com/avatars/hana_kim.jpg",
    "lang_tag": "ko-KR",
    "timezone": "Asia/Seoul",
    "created_at": "2025-02-05T05:15:00Z",
    "updated_at": "2025-03-01T10:40:00Z",
    "verified_at": "2025-02-06T07:20:00Z"
  },
  {
    "id": "550e8400-e29b-41d4-a716-446655440021",
    "username": "jack_thompson",
    "display_name": "Jack Thompson",
    "email": "jack.thompson@example.com",
    "country": "United States",
    "state": "Texas",
    "avatar_url": "https://cdn.example.com/avatars/jack_thompson.jpg",
    "lang_tag": "en-US",
    "timezone": "America/Chicago",
    "created_at": "2025-02-07T08:00:00Z",
    "updated_at": "2025-03-02T09:15:00Z",
    "verified_at": "2025-02-08T07:45:00Z"
  },
  {
    "id": "550e8400-e29b-41d4-a716-446655440022",
    "username": "amelia_clark",
    "display_name": "Amelia Clark",
    "email": "amelia.clark@example.com",
    "country": "Canada",
    "state": "British Columbia",
    "avatar_url": "https://cdn.example.com/avatars/amelia_clark.jpg",
    "lang_tag": "en-CA",
    "timezone": "America/Vancouver",
    "created_at": "2025-02-08T10:30:00Z",
    "updated_at": "2025-03-03T08:20:00Z",
    "verified_at": "2025-02-09T09:00:00Z"
  },
  {
    "id": "550e8400-e29b-41d4-a716-446655440023",
    "username": "diego_martinez",
    "display_name": "Diego Martinez",
    "email": "diego.martinez@example.com",
    "country": "Argentina",
    "state": "Buenos Aires",
    "avatar_url": "https://cdn.example.com/avatars/diego_martinez.jpg",
    "lang_tag": "es-AR",
    "timezone": "America/Argentina/Buenos_Aires",
    "created_at": "2025-02-09T06:40:00Z",
    "updated_at": "2025-03-04T11:30:00Z",
    "verified_at": "2025-02-10T08:10:00Z"
  },
  {
    "id": "550e8400-e29b-41d4-a716-446655440024",
    "username": "priya_sharma",
    "display_name": "Priya Sharma",
    "email": "priya.sharma@example.com",
    "country": "India",
    "state": "Maharashtra",
    "avatar_url": "https://cdn.example.com/avatars/priya_sharma.jpg",
    "lang_tag": "en-IN",
    "timezone": "Asia/Kolkata",
    "created_at": "2025-02-10T05:10:00Z",
    "updated_at": "2025-03-05T12:45:00Z",
    "verified_at": "2025-02-11T07:00:00Z"
  },
  {
    "id": "550e8400-e29b-41d4-a716-446655440025",
    "username": "ahmed_ali",
    "display_name": "Ahmed Ali",
    "email": "ahmed.ali@example.com",
    "country": "United Arab Emirates",
    "state": "Dubai",
    "avatar_url": "https://cdn.example.com/avatars/ahmed_ali.jpg",
    "lang_tag": "ar-AE",
    "timezone": "Asia/Dubai",
    "created_at": "2025-02-11T09:20:00Z",
    "updated_at": "2025-03-06T10:10:00Z",
    "verified_at": "2025-02-12T08:00:00Z"
  },
  {
    "id": "550e8400-e29b-41d4-a716-446655440026",
    "username": "elena_petrova",
    "display_name": "Elena Petrova",
    "email": "elena.petrova@example.com",
    "country": "Bulgaria",
    "state": "Sofia",
    "avatar_url": "https://cdn.example.com/avatars/elena_petrova.jpg",
    "lang_tag": "bg-BG",
    "timezone": "Europe/Sofia",
    "created_at": "2025-02-12T07:35:00Z",
    "updated_at": "2025-03-07T14:00:00Z",
    "verified_at": "2025-02-13T09:10:00Z"
  },
  {
    "id": "550e8400-e29b-41d4-a716-446655440027",
    "username": "samuel_okafor",
    "display_name": "Samuel Okafor",
    "email": "samuel.okafor@example.com",
    "country": "Nigeria",
    "state": "Lagos",
    "avatar_url": "https://cdn.example.com/avatars/samuel_okafor.jpg",
    "lang_tag": "en-NG",
    "timezone": "Africa/Lagos",
    "created_at": "2025-02-13T08:25:00Z",
    "updated_at": "2025-03-08T09:50:00Z",
    "verified_at": "2025-02-14T07:55:00Z"
  },
  {
    "id": "550e8400-e29b-41d4-a716-446655440028",
    "username": "freja_nielsen",
    "display_name": "Freja Nielsen",
    "email": "freja.nielsen@example.com",
    "country": "Denmark",
    "state": "Zealand",
    "avatar_url": "https://cdn.example.com/avatars/freja_nielsen.jpg",
    "lang_tag": "da-DK",
    "timezone": "Europe/Copenhagen",
    "created_at": "2025-02-14T06:15:00Z",
    "updated_at": "2025-03-09T10:20:00Z",
    "verified_at": "2025-02-15T08:35:00Z"
  },
  {
    "id": "550e8400-e29b-41d4-a716-446655440029",
    "username": "miguel_rodriguez",
    "display_name": "Miguel Rodriguez",
    "email": "miguel.rodriguez@example.com",
    "country": "Chile",
    "state": "Santiago Metropolitan",
    "avatar_url": "https://cdn.example.com/avatars/miguel_rodriguez.jpg",
    "lang_tag": "es-CL",
    "timezone": "America/Santiago",
    "created_at": "2025-02-15T05:45:00Z",
    "updated_at": "2025-03-10T13:30:00Z",
    "verified_at": "2025-02-16T07:40:00Z"
  },
  {
    "id": "550e8400-e29b-41d4-a716-446655440030",
    "username": "sakura_yamamoto",
    "display_name": "Sakura Yamamoto",
    "email": "sakura.yamamoto@example.com",
    "country": "Japan",
    "state": "Osaka",
    "avatar_url": "https://cdn.example.com/avatars/sakura_yamamoto.jpg",
    "lang_tag": "ja-JP",
    "timezone": "Asia/Tokyo",
    "created_at": "2025-02-16T04:50:00Z",
    "updated_at": "2025-03-11T09:40:00Z",
    "verified_at": "2025-02-17T06:25:00Z"
  },
  {
    "id": "550e8400-e29b-41d4-a716-446655440031",
    "username": "charlotte_evans",
    "display_name": "Charlotte Evans",
    "email": "charlotte.evans@example.com",
    "country": "United Kingdom",
    "state": "Scotland",
    "avatar_url": "https://cdn.example.com/avatars/charlotte_evans.jpg",
    "lang_tag": "en-GB",
    "timezone": "Europe/London",
    "created_at": "2025-02-17T08:20:00Z",
    "updated_at": "2025-03-12T10:10:00Z",
    "verified_at": "2025-02-18T07:30:00Z"
  },
  {
    "id": "550e8400-e29b-41d4-a716-446655440032",
    "username": "benjamin_hughes",
    "display_name": "Benjamin Hughes",
    "email": "benjamin.hughes@example.com",
    "country": "Australia",
    "state": "Victoria",
    "avatar_url": "https://cdn.example.com/avatars/benjamin_hughes.jpg",
    "lang_tag": "en-AU",
    "timezone": "Australia/Melbourne",
    "created_at": "2025-02-18T06:45:00Z",
    "updated_at": "2025-03-13T09:25:00Z",
    "verified_at": "2025-02-19T08:40:00Z"
  },
  {
    "id": "550e8400-e29b-41d4-a716-446655440033",
    "username": "camila_alvarez",
    "display_name": "Camila Alvarez",
    "email": "camila.alvarez@example.com",
    "country": "Colombia",
    "state": "Bogota",
    "avatar_url": "https://cdn.example.com/avatars/camila_alvarez.jpg",
    "lang_tag": "es-CO",
    "timezone": "America/Bogota",
    "created_at": "2025-02-19T05:30:00Z",
    "updated_at": "2025-03-14T12:00:00Z",
    "verified_at": "2025-02-20T07:15:00Z"
  },
  {
    "id": "550e8400-e29b-41d4-a716-446655440034",
    "username": "rohan_mehta",
    "display_name": "Rohan Mehta",
    "email": "rohan.mehta@example.com",
    "country": "India",
    "state": "Karnataka",
    "avatar_url": "https://cdn.example.com/avatars/rohan_mehta.jpg",
    "lang_tag": "en-IN",
    "timezone": "Asia/Kolkata",
    "created_at": "2025-02-20T04:10:00Z",
    "updated_at": "2025-03-15T11:35:00Z",
    "verified_at": "2025-02-21T06:50:00Z"
  },
  {
    "id": "550e8400-e29b-41d4-a716-446655440035",
    "username": "fatima_rahman",
    "display_name": "Fatima Rahman",
    "email": "fatima.rahman@example.com",
    "country": "Bangladesh",
    "state": "Dhaka",
    "avatar_url": "https://cdn.example.com/avatars/fatima_rahman.jpg",
    "lang_tag": "bn-BD",
    "timezone": "Asia/Dhaka",
    "created_at": "2025-02-21T07:25:00Z",
    "updated_at": "2025-03-16T08:55:00Z",
    "verified_at": "2025-02-22T09:00:00Z"
  },
  {
    "id": "550e8400-e29b-41d4-a716-446655440036",
    "username": "nikola_jovanovic",
    "display_name": "Nikola Jovanovic",
    "email": "nikola.jovanovic@example.com",
    "country": "Serbia",
    "state": "Belgrade",
    "avatar_url": "https://cdn.example.com/avatars/nikola_jovanovic.jpg",
    "lang_tag": "sr-RS",
    "timezone": "Europe/Belgrade",
    "created_at": "2025-02-22T06:20:00Z",
    "updated_at": "2025-03-17T10:45:00Z",
    "verified_at": "2025-02-23T07:10:00Z"
  },
  {
    "id": "550e8400-e29b-41d4-a716-446655440037",
    "username": "grace_walker",
    "display_name": "Grace Walker",
    "email": "grace.walker@example.com",
    "country": "New Zealand",
    "state": "Wellington",
    "avatar_url": "https://cdn.example.com/avatars/grace_walker.jpg",
    "lang_tag": "en-NZ",
    "timezone": "Pacific/Auckland",
    "created_at": "2025-02-23T05:50:00Z",
    "updated_at": "2025-03-18T09:30:00Z",
    "verified_at": "2025-02-24T08:15:00Z"
  },
  {
    "id": "550e8400-e29b-41d4-a716-446655440038",
    "username": "luca_bianchi",
    "display_name": "Luca Bianchi",
    "email": "luca.bianchi@example.com",
    "country": "Italy",
    "state": "Tuscany",
    "avatar_url": "https://cdn.example.com/avatars/luca_bianchi.jpg",
    "lang_tag": "it-IT",
    "timezone": "Europe/Rome",
    "created_at": "2025-02-24T09:15:00Z",
    "updated_at": "2025-03-19T11:20:00Z",
    "verified_at": "2025-02-25T07:45:00Z"
  },
  {
    "id": "550e8400-e29b-41d4-a716-446655440039",
    "username": "thandi_mokoena",
    "display_name": "Thandi Mokoena",
    "email": "thandi.mokoena@example.com",
    "country": "South Africa",
    "state": "Gauteng",
    "avatar_url": "https://cdn.example.com/avatars/thandi_mokoena.jpg",
    "lang_tag": "en-ZA",
    "timezone": "Africa/Johannesburg",
    "created_at": "2025-02-25T08:40:00Z",
    "updated_at": "2025-03-20T10:50:00Z",
    "verified_at": "2025-02-26T09:20:00Z"
  },
  {
    "id": "550e8400-e29b-41d4-a716-446655440040",
    "username": "minseo_park",
    "display_name": "Minseo Park",
    "email": "minseo.park@example.com",
    "country": "South Korea",
    "state": "Busan",
    "avatar_url": "https://cdn.example.com/avatars/minseo_park.jpg",
    "lang_tag": "ko-KR",
    "timezone": "Asia/Seoul",
    "created_at": "2025-02-26T07:10:00Z",
    "updated_at": "2025-03-21T09:40:00Z",
    "verified_at": "2025-02-27T08:05:00Z"
  },
  {
    "id": "550e8400-e29b-41d4-a716-446655440041",
    "username": "ethan_miller",
    "display_name": "Ethan Miller",
    "email": "ethan.miller@example.com",
    "country": "United States",
    "state": "New York",
    "avatar_url": "https://cdn.example.com/avatars/ethan_miller.jpg",
    "lang_tag": "en-US",
    "timezone": "America/New_York",
    "created_at": "2025-02-27T08:00:00Z",
    "updated_at": "2025-03-22T09:15:00Z",
    "verified_at": "2025-02-28T07:30:00Z"
  },
  {
    "id": "550e8400-e29b-41d4-a716-446655440042",
    "username": "chloe_martin",
    "display_name": "Chloe Martin",
    "email": "chloe.martin@example.com",
    "country": "France",
    "state": "Provence-Alpes-Cote d'Azur",
    "avatar_url": "https://cdn.example.com/avatars/chloe_martin.jpg",
    "lang_tag": "fr-FR",
    "timezone": "Europe/Paris",
    "created_at": "2025-02-28T06:20:00Z",
    "updated_at": "2025-03-23T10:40:00Z",
    "verified_at": "2025-03-01T08:10:00Z"
  },
  {
    "id": "550e8400-e29b-41d4-a716-446655440043",
    "username": "daniel_kowalski",
    "display_name": "Daniel Kowalski",
    "email": "daniel.kowalski@example.com",
    "country": "Poland",
    "state": "Masovian",
    "avatar_url": "https://cdn.example.com/avatars/daniel_kowalski.jpg",
    "lang_tag": "pl-PL",
    "timezone": "Europe/Warsaw",
    "created_at": "2025-03-01T07:35:00Z",
    "updated_at": "2025-03-24T11:00:00Z",
    "verified_at": "2025-03-02T08:45:00Z"
  },
  {
    "id": "550e8400-e29b-41d4-a716-446655440044",
    "username": "ananya_reddy",
    "display_name": "Ananya Reddy",
    "email": "ananya.reddy@example.com",
    "country": "India",
    "state": "Telangana",
    "avatar_url": "https://cdn.example.com/avatars/ananya_reddy.jpg",
    "lang_tag": "en-IN",
    "timezone": "Asia/Kolkata",
    "created_at": "2025-03-02T05:10:00Z",
    "updated_at": "2025-03-25T09:55:00Z",
    "verified_at": "2025-03-03T07:25:00Z"
  },
  {
    "id": "550e8400-e29b-41d4-a716-446655440045",
    "username": "youssef_benali",
    "display_name": "Youssef Benali",
    "email": "youssef.benali@example.com",
    "country": "Morocco",
    "state": "Casablanca-Settat",
    "avatar_url": "https://cdn.example.com/avatars/youssef_benali.jpg",
    "lang_tag": "ar-MA",
    "timezone": "Africa/Casablanca",
    "created_at": "2025-03-03T08:15:00Z",
    "updated_at": "2025-03-26T10:35:00Z",
    "verified_at": "2025-03-04T09:00:00Z"
  },
  {
    "id": "550e8400-e29b-41d4-a716-446655440046",
    "username": "isabella_rossi",
    "display_name": "Isabella Rossi",
    "email": "isabella.rossi@example.com",
    "country": "Italy",
    "state": "Lazio",
    "avatar_url": "https://cdn.example.com/avatars/isabella_rossi.jpg",
    "lang_tag": "it-IT",
    "timezone": "Europe/Rome",
    "created_at": "2025-03-04T06:40:00Z",
    "updated_at": "2025-03-27T11:20:00Z",
    "verified_at": "2025-03-05T08:15:00Z"
  },
  {
    "id": "550e8400-e29b-41d4-a716-446655440047",
    "username": "joao_pereira",
    "display_name": "Joao Pereira",
    "email": "joao.pereira@example.com",
    "country": "Portugal",
    "state": "Lisbon",
    "avatar_url": "https://cdn.example.com/avatars/joao_pereira.jpg",
    "lang_tag": "pt-PT",
    "timezone": "Europe/Lisbon",
    "created_at": "2025-03-05T07:00:00Z",
    "updated_at": "2025-03-28T12:10:00Z",
    "verified_at": "2025-03-06T08:40:00Z"
  },
  {
    "id": "550e8400-e29b-41d4-a716-446655440048",
    "username": "aisha_yusuf",
    "display_name": "Aisha Yusuf",
    "email": "aisha.yusuf@example.com",
    "country": "Nigeria",
    "state": "Abuja",
    "avatar_url": "https://cdn.example.com/avatars/aisha_yusuf.jpg",
    "lang_tag": "en-NG",
    "timezone": "Africa/Lagos",
    "created_at": "2025-03-06T05:55:00Z",
    "updated_at": "2025-03-29T09:45:00Z",
    "verified_at": "2025-03-07T07:30:00Z"
  },
  {
    "id": "550e8400-e29b-41d4-a716-446655440049",
    "username": "matej_novak",
    "display_name": "Matej Novak",
    "email": "matej.novak@example.com",
    "country": "Slovakia",
    "state": "Bratislava",
    "avatar_url": "https://cdn.example.com/avatars/matej_novak.jpg",
    "lang_tag": "sk-SK",
    "timezone": "Europe/Bratislava",
    "created_at": "2025-03-07T08:20:00Z",
    "updated_at": "2025-03-30T10:25:00Z",
    "verified_at": "2025-03-08T08:50:00Z"
  },
  {
    "id": "550e8400-e29b-41d4-a716-446655440050",
    "username": "mei_lin",
    "display_name": "Mei Lin",
    "email": "mei.lin@example.com",
    "country": "Singapore",
    "state": "Central Region",
    "avatar_url": "https://cdn.example.com/avatars/mei_lin.jpg",
    "lang_tag": "en-SG",
    "timezone": "Asia/Singapore",
    "created_at": "2025-03-08T06:10:00Z",
    "updated_at": "2025-03-31T11:30:00Z",
    "verified_at": "2025-03-09T07:40:00Z"
  }
]